ucolor/__init__.py
ucolor/color_hsla.py
ucolor/color_hsva.py
ucolor/color_rgba.py
ucolor/convert.py
ucolor/utils.py
ucolor-0.2.0.dist-info/METADATA
ucolor-0.2.0.dist-info/WHEEL
ucolor-0.2.0.dist-info/RECORD
