Metadata-Version: 2.1
Name: ucolor
Version: 0.2.0
Summary: UltraCOLOR is a powerful color library
Author: Aserogl
Author-email: aserogl31@gmail.com
Requires-Python: >=3.8
Classifier: Programming Language :: Python :: 3
Classifier: Programming Language :: Python :: 3.8
Classifier: Programming Language :: Python :: 3.9
Classifier: Programming Language :: Python :: 3.10
Classifier: Programming Language :: Python :: 3.11
